siglent/__init__.py
siglent/_common.py
siglent/_device.py
siglent/sdl1000x/__init__.py
siglent/sdl1000x/_sdl1000x.py
siglent/spd3303x/__init__.py
siglent/spd3303x/_spd3303x.py
siglent_vxi11-0.0.12.dist-info/LICENSE
siglent_vxi11-0.0.12.dist-info/METADATA
siglent_vxi11-0.0.12.dist-info/WHEEL
siglent_vxi11-0.0.12.dist-info/top_level.txt
siglent_vxi11-0.0.12.dist-info/RECORD
