Metadata-Version: 2.1
Name: siglent-vxi11
Version: 0.0.12
Summary: Siglent vxi11 library
Home-page: UNKNOWN
Author: Richard Waschhauser
License: UNKNOWN
Keywords: Siglent,VXI,SDL1020X-E,SPD3303X,SPD3303X-E
Platform: UNKNOWN
Classifier: Development Status :: 2 - Pre-Alpha
Classifier: Operating System :: OS Independent
Classifier: Programming Language :: Python :: 3
Classifier: Programming Language :: Python :: 3.5
Classifier: Programming Language :: Python :: 3.6
Classifier: Programming Language :: Python :: 3.7
Classifier: Programming Language :: Python :: 3.8
Classifier: License :: OSI Approved :: MIT License
Classifier: Topic :: System :: Hardware :: Hardware Drivers
Classifier: Topic :: System :: Networking
Requires-Python: >=3.5
Requires-Dist: python-vxi11
